pydips/__init__.py
pydips/api.py
pydips/model.py
pydips/utils.py
pydips/binaries/linux/libbert.so
pydips/binaries/linux/libggml.so
pydips/binaries/macos/libbert.dylib
pydips/binaries/macos/libggml.dylib
pydips/models/electra-small-6-layers-q4_0.gguf
pydips-0.0.4.dist-info/LICENSE
pydips-0.0.4.dist-info/METADATA
pydips-0.0.4.dist-info/WHEEL
pydips-0.0.4.dist-info/top_level.txt
pydips-0.0.4.dist-info/RECORD
