Metadata-Version: 2.1
Name: pydips
Version: 0.0.4
Summary: Multi-criteria Cantonese segmentation with dashes, intermediates, pipes, and spaces.
Author-email: Kevin Xiang Li <kevinli020508@gmail.com>
License: MIT
Project-URL: Homepage, https://github.com/AlienKevin/pydips
Project-URL: Bug Reports, https://github.com/AlienKevin/pydips/issues
Project-URL: Source, https://github.com/AlienKevin/pydips
Keywords: cantonese,chinese,natural-language-processing
Classifier: Development Status :: 4 - Beta
Classifier: Intended Audience :: Developers
Classifier: Topic :: Software Development :: Libraries :: Python Modules
Classifier: Topic :: Text Processing :: Linguistic
Classifier: Natural Language :: Cantonese
Classifier: Natural Language :: Chinese (Traditional)
Classifier: Operating System :: MacOS :: MacOS X
Classifier: Operating System :: POSIX :: Linux
Classifier: License :: OSI Approved :: MIT License
Classifier: Programming Language :: Python :: 3
Classifier: Programming Language :: Python :: 3.9
Classifier: Programming Language :: Python :: 3.10
Classifier: Programming Language :: Python :: 3.11
Classifier: Programming Language :: Python :: 3.12
Requires-Python: <4,>=3.9
License-File: LICENSE
